kripta_py/__init__.py
kripta_py/asymmetric.py
kripta_py/symmetric.py
kripta_py-0.1.3.dist-info/WHEEL
kripta_py-0.1.3.dist-info/METADATA
kripta_py-0.1.3.dist-info/RECORD
