Metadata-Version: 2.1
Name: kripta-py
Version: 0.1.3
Summary: A tiny asymmetric/symmetric encryption lib for humans.
Home-page: https://github.com/Sanix-Darker/kripta-py
License: MIT
Keywords: AES,RSA,encryption,decryption
Author: sanix-darker
Author-email: s4nixd@gmail.com
Requires-Python: >=3.8,<4.0
Classifier: License :: OSI Approved :: MIT License
Classifier: Programming Language :: Python :: 3
Classifier: Programming Language :: Python :: 3.10
Classifier: Programming Language :: Python :: 3.8
Classifier: Programming Language :: Python :: 3.9
Requires-Dist: pycryptodome (>=3.14.1,<4)
Project-URL: Repository, https://github.com/Sanix-Darker/kripta-py
